dyns/__init__.py
dyns/dyns.py
dyns-1.3.1.data/scripts/dynsctl
dyns-1.3.1.dist-info/LICENSE
dyns-1.3.1.dist-info/METADATA
dyns-1.3.1.dist-info/WHEEL
dyns-1.3.1.dist-info/top_level.txt
dyns-1.3.1.dist-info/RECORD
