Metadata-Version: 2.1
Name: dyns
Version: 1.3.1
Summary: Command line tool to interact with dyns API
Home-page: https://github.com/xhs/dyns/dynsctl
Author: Xiaohan Song
Author-email: chef@dark.kitchen
License: UNKNOWN
Platform: UNKNOWN
Classifier: Development Status :: 4 - Beta
Classifier: License :: OSI Approved :: MIT License
Classifier: Programming Language :: Python :: 3.6
Classifier: Programming Language :: Python :: 3.7
Classifier: Programming Language :: Python :: 3.8
Requires-Python: >=3.6
Requires-Dist: click (>=7.1.2)
Requires-Dist: requests (>=2.23.0)
Requires-Dist: rich (>=1.2.2)
Requires-Dist: toml (>=0.10.1)
